function_error_handling.py
function_error_handling/__init__.py
function_error_handling/function_error_handling.py
function_error_handling/validators.py
trython/__init__.py
trython/trython.py
trython/validators.py
trython-3.3.0.dist-info/LICENSE
trython-3.3.0.dist-info/METADATA
trython-3.3.0.dist-info/WHEEL
trython-3.3.0.dist-info/top_level.txt
trython-3.3.0.dist-info/RECORD
